{
  "pages": [
    {
      "path": "pages/index/index",
      "style": {
        "navigationBarTitleText": "伯乐简历",
        "enablePullDownRefresh": true
      }
    },
    {
      "path": "pages/follow/follow",
      "style": {
        "navigationBarTitleText": "关注",
        "enablePullDownRefresh": true
      }
    },
    {
      "path": "pages/message/message",
      "style": {
        "navigationBarTitleText": "消息",
        "enablePullDownRefresh": true
      }
    },
    {
      "path": "pages/profile/profile",
      "style": {
        "navigationBarTitleText": "我的",
        "enablePullDownRefresh": false
      }
	}
  ],
  "tabBar": {
    "color": "#666666",
    "selectedColor": "#d4af37",
    "backgroundColor": "#ffffff",
    "borderStyle": "black",
    "list": [
      {
        "pagePath": "pages/index/index",
        "iconPath": "static/tabbar/home.png",
        "selectedIconPath": "static/tabbar/home-active.png",
        "text": "首页"
      },
      {
        "pagePath": "pages/follow/follow",
        "iconPath": "static/tabbar/follow.png",
        "selectedIconPath": "static/tabbar/follow-active.png",
        "text": "关注"
      },
      {
        "pagePath": "pages/message/message",
        "iconPath": "static/tabbar/message.png",
        "selectedIconPath": "static/tabbar/message-active.png",
        "text": "消息"
      },
      {
        "pagePath": "pages/profile/profile",
        "iconPath": "static/tabbar/profile.png",
        "selectedIconPath": "static/tabbar/profile-active.png",
        "text": "我的"
      }
    ]
  },
  "globalStyle": {
    "navigationBarTextStyle": "black",
    "navigationBarTitleText": "伯乐简历",
    "navigationBarBackgroundColor": "#ffffff",
    "backgroundColor": "#f8f8f8",
    "app-plus": {
      "background": "#efeff4"
    }
  }
}